django_extra_referrals/__init__.py
django_extra_referrals/admin.py
django_extra_referrals/apps.py
django_extra_referrals/feeschema.py
django_extra_referrals/middleware.py
django_extra_referrals/models.py
django_extra_referrals/views.py
django_extra_referrals/migrations/__init__.py
django_extra_referrals/utils/__init__.py
django_extra_referrals/utils/version.py
django_extra_referrals-0.0.1.dist-info/LICENSE
django_extra_referrals-0.0.1.dist-info/METADATA
django_extra_referrals-0.0.1.dist-info/WHEEL
django_extra_referrals-0.0.1.dist-info/top_level.txt
django_extra_referrals-0.0.1.dist-info/RECORD
