Metadata-Version: 2.1
Name: django-extra-referrals
Version: 0.0.1
Summary: Django referral with multilevel fee system
Home-page: https://github.com/sasriawesome/django_extra_referrals
Maintainer: Rizki Sasri Dwitama
Maintainer-email: sasri.project@gmail.com
License: MIT
Platform: UNKNOWN
Classifier: Development Status :: 3 - Alpha
Classifier: Environment :: Web Environment
Classifier: Framework :: Django
Classifier: Intended Audience :: Developers
Classifier: License :: OSI Approved :: BSD License
Classifier: Operating System :: OS Independent
Classifier: Programming Language :: Python
Classifier: Topic :: Software Development :: Libraries :: Python Modules
Requires-Dist: django (>=2.2)
Requires-Dist: django-numerators (>=0.0.1)
Requires-Dist: django-polymorphic (>=2.1.2)
Requires-Dist: django-mptt (>=0.11.0)
